README.md
setup.py
src/testgear_adapter_behave/__init__.py
src/testgear_adapter_behave/formatter.py
src/testgear_adapter_behave/listener.py
src/testgear_adapter_behave/scenario_parser.py
src/testgear_adapter_behave/tags_parser.py
src/testgear_adapter_behave/utils.py
src/testgear_adapter_behave.egg-info/PKG-INFO
src/testgear_adapter_behave.egg-info/SOURCES.txt
src/testgear_adapter_behave.egg-info/dependency_links.txt
src/testgear_adapter_behave.egg-info/requires.txt
src/testgear_adapter_behave.egg-info/top_level.txt
src/testgear_adapter_behave/models/__init__.py
src/testgear_adapter_behave/models/label.py
src/testgear_adapter_behave/models/option.py
src/testgear_adapter_behave/models/tags.py
src/testgear_adapter_behave/models/test_result_step.py
src/testgear_adapter_behave/models/url_link.py